semaphoreui_client/__about__.py
semaphoreui_client/__init__.py
semaphoreui_client/client.py
semaphoreui_client-0.2.2.dist-info/METADATA
semaphoreui_client-0.2.2.dist-info/WHEEL
semaphoreui_client-0.2.2.dist-info/RECORD
